dinosource/__init__.py
dinosource-0.0.1.dist-info/LICENSE
dinosource-0.0.1.dist-info/METADATA
dinosource-0.0.1.dist-info/WHEEL
dinosource-0.0.1.dist-info/top_level.txt
dinosource-0.0.1.dist-info/RECORD
